{"tutorials":[{"difficulty":"中等","totalDuration":"6小时30分钟","progress":"100%","updateTime":"2025-07-27","articleCount":13,"id":1,"title":"微积分学习笔记","category":"9","articles":[{"difficulty":"中等","duration":"30分钟","filename":"series_1/9-1-1.md","id":"1-1","title":"第一章：导数","order":1},{"difficulty":"中等","duration":"30分钟","filename":"series_1/9-1-2.md","id":"1-2","title":"第二章：积分基础","order":2},{"difficulty":"中等","duration":"30分钟","filename":"series_1/9-1-3.md","id":"1-3","title":"第三章：极限与连续性","order":3},{"difficulty":"中等","duration":"30分钟","filename":"series_1/9-1-7.md","id":"1-4","title":"高考导数应用","order":4},{"difficulty":"中等","duration":"30分钟","filename":"series_1/9-1-8.md","id":"1-5","title":"中考函数专题","order":5},{"difficulty":"中等","duration":"30分钟","filename":"series_1/9-1-9.md","id":"1-6","title":"一次函数基础","order":6},{"difficulty":"中等","duration":"30分钟","filename":"series_1/9-1-10.md","id":"1-7","title":"二次函数图像与性质","order":7},{"difficulty":"中等","duration":"30分钟","filename":"series_1/9-1-11.md","id":"1-8","title":"函数综合练习","order":8},{"difficulty":"中等","duration":"30分钟","filename":"series_1/9-1-12.md","id":"1-9","title":"中考几何证明","order":9},{"difficulty":"中等","duration":"30分钟","filename":"series_1/9-1-13.md","id":"1-10","title":"三角形全等证明","order":10},{"difficulty":"中等","duration":"30分钟","filename":"series_1/9-1-14.md","id":"1-11","title":"小学分数运算","order":11},{"difficulty":"中等","duration":"30分钟","filename":"series_1/9-1-15.md","id":"1-12","title":"角平分线相关问题模型","order":12},{"difficulty":"中等","duration":"30分钟","filename":"series_1/9-1-16.md","id":"1-13","title":"一、选择题","order":13}],"desc":"完整的微积分学习笔记，包含导数、积分、极限等核心概念","tags":["微积分","数学分析"]},{"difficulty":"中等","totalDuration":"1小时0分钟","progress":"100%","updateTime":"2025-07-27","articleCount":2,"id":2,"title":"线性代数基础","category":"9","articles":[{"difficulty":"中等","duration":"30分钟","filename":"series_2/9-2-4.md","id":"2-1","title":"矩阵运算基础","order":1},{"difficulty":"中等","duration":"30分钟","filename":"series_2/9-2-5.md","id":"2-2","title":"向量空间与线性变换","order":2}],"desc":"线性代数基础知识整理，包含矩阵运算、向量空间等","tags":["线性代数","矩阵"]},{"difficulty":"中等","totalDuration":"30分钟","progress":"100%","updateTime":"2025-07-27","articleCount":1,"id":3,"title":"概率统计入门","category":"9","articles":[{"difficulty":"中等","duration":"30分钟","filename":"series_3/9-3-6.md","id":"3-1","title":"概率论基础","order":1}],"desc":"概率论与数理统计入门教程","tags":["概率统计","数据分析"]}],"meta":{"totalTutorials":3,"totalArticles":16,"lastUpdate":"2025-07-27","version":"1.0.0"}}